logguard/__init__.py
logguard/decorator.py
logguard/handler.py
logguard/redactor.py
logguard-2.0.0.dist-info/licenses/LICENSE
logguard-2.0.0.dist-info/METADATA
logguard-2.0.0.dist-info/WHEEL
logguard-2.0.0.dist-info/top_level.txt
logguard-2.0.0.dist-info/RECORD
