Metadata-Version: 2.4
Name: logguard
Version: 2.0.0
Summary: Automatic redaction utilities for logging to prevent sensitive data leaks
Author-email: Syed Rakesh Uddin <syedrakeshuddin@gmail.com>
License: MIT
Keywords: logging,redaction,security,sensitive,privacy
Requires-Python: >=3.8
License-File: LICENSE
Dynamic: license-file
